<?xml version="1.0" encoding="utf-8" ?>
<?xml-stylesheet type="text/xsl" href="Bai2.xslt"?>

<Lop xmlns="http://tempuri.org/Bai2.xsd">
	<SinhVien>
		<MaSv>sv01</MaSv>
		<TenSv>Nguyễn Văn A</TenSv>
		<GioiTinh>Nam</GioiTinh>
		<NgaySinh>2002-11-03</NgaySinh>
		<MaLop>CNTT01</MaLop>
	</SinhVien>
	<SinhVien>
		<MaSv>sv02</MaSv>
		<TenSv>Nguyễn Văn B</TenSv>
		<GioiTinh>Nam</GioiTinh>
		<NgaySinh>2002-11-03</NgaySinh>
		<MaLop>CNTT01</MaLop>
	</SinhVien>
	<SinhVien>
		<MaSv>sv03</MaSv>
		<TenSv>Nguyễn Văn D</TenSv>
		<GioiTinh>Nam</GioiTinh>
		<NgaySinh>2002-11-03</NgaySinh>
		<MaLop>CNTT01</MaLop>
	</SinhVien>
	<SinhVien>
		<MaSv>sv04</MaSv>
		<TenSv>Nguyễn Văn C</TenSv>
		<GioiTinh>Nam</GioiTinh>
		<NgaySinh>2002-11-03</NgaySinh>
		<MaLop>CNTT01</MaLop>
	</SinhVien>
</Lop>
